examples/__init__.py
examples/g3/__init__.py
examples/g3/entitiesToExcel.py
examples/g3/languageToExcel.py
examples/g3/quickStart.py
examples/g3/quickStartAll.py
examples/g3/quickStartEntities.py
examples/g3/relationsToExcel.py
examples/g3/sentimentToExcel.py
geneeanlpclient/__init__.py
geneeanlpclient/common/__init__.py
geneeanlpclient/common/common.py
geneeanlpclient/common/dictutil.py
geneeanlpclient/common/restutil.py
geneeanlpclient/common/ud.py
geneeanlpclient/g3/__init__.py
geneeanlpclient/g3/client.py
geneeanlpclient/g3/f2converter.py
geneeanlpclient/g3/model.py
geneeanlpclient/g3/reader.py
geneeanlpclient/g3/request.py
geneeanlpclient/g3/writer.py
tests/__init__.py
tests/geneeanlpclient/__init__.py
tests/geneeanlpclient/common/__init__.py
tests/geneeanlpclient/common/test_common.py
tests/geneeanlpclient/common/test_jsonutil.py
tests/geneeanlpclient/common/test_ud.py
tests/geneeanlpclient/g3/__init__.py
tests/geneeanlpclient/g3/examples.py
tests/geneeanlpclient/g3/generate.py
tests/geneeanlpclient/g3/test_analysis.py
tests/geneeanlpclient/g3/test_charSpan.py
tests/geneeanlpclient/g3/test_f2converter.py
tests/geneeanlpclient/g3/test_model.py
tests/geneeanlpclient/g3/test_request.py
tests/geneeanlpclient/g3/test_rw.py
tests/geneeanlpclient/g3/test_tokenSupport.py
tests/geneeanlpclient/g3/test_tokenutils.py
tests/geneeanlpclient/g3/test_treeBuilder.py
geneea_nlp_client-1.5.1.dist-info/LICENSE
geneea_nlp_client-1.5.1.dist-info/METADATA
geneea_nlp_client-1.5.1.dist-info/WHEEL
geneea_nlp_client-1.5.1.dist-info/top_level.txt
geneea_nlp_client-1.5.1.dist-info/RECORD
