Metadata-Version: 2.1
Name: geneea-nlp-client
Version: 1.5.1
Summary: The SDK library and command-line interface to Geneea Interpretor, an NLP REST API.
Home-page: https://geneea.com
Author: Geneea Analytics s.r.o
Author-email: support@geneea.com
License: UNKNOWN
Project-URL: Documentation, https://help.geneea.com/sdk/index.html
Project-URL: Source Code, https://bitbucket.org/geneea/sdk
Keywords: geneea python interpretor nlp nlu api cli
Platform: UNKNOWN
Classifier: Development Status :: 3 - Alpha
Classifier: Programming Language :: Python :: 3 :: Only
Classifier: Programming Language :: Python :: 3.8
Classifier: Programming Language :: Python :: 3.9
Classifier: Programming Language :: Python :: 3.10
Classifier: Programming Language :: Python :: 3.11
Classifier: Programming Language :: Python :: 3.12
Classifier: Programming Language :: Python :: 3.13
Classifier: License :: OSI Approved :: Apache Software License
License-File: LICENSE
Requires-Dist: requests ~=2.25
Requires-Dist: retrying ~=1.3
Provides-Extra: examples
Requires-Dist: pandas >=0.22 ; extra == 'examples'
